my_lib/__init__.py
my_lib/test.py
my_lib/dataStructures/__init__.py
my_lib/dataStructures/linear_test.py
my_lib/dataStructures/linear/__init__.py
my_lib/dataStructures/linear/cdll.py
my_lib/dataStructures/linear/cdll_test.py
my_lib/dataStructures/linear/csll.py
my_lib/dataStructures/linear/dll.py
my_lib/dataStructures/linear/queue_ll.py
my_lib/dataStructures/linear/sll.py
my_lib/dataStructures/linear/stack_ll.py
my_lib/dataStructures/nodes/TNode.py
my_lib/dataStructures/nodes/__init__.py
my_lib/dataStructures/nodes/d_node.py
my_lib/dataStructures/nodes/s_node.py
my_lib/dataStructures/trees/AVL.py
my_lib/dataStructures/trees/AVL_test.py
my_lib/dataStructures/trees/BST.py
my_lib/dataStructures/trees/__init__.py
my_lib/dataStructures/trees/main.py
my_lib/dataStructures/trees/test_AVL.py
my_lib/dataStructures/trees/test_BST.py
my_lib/dataStructures/trees/test_TNode.py
41datastructure-1.5.dist-info/METADATA
41datastructure-1.5.dist-info/WHEEL
41datastructure-1.5.dist-info/top_level.txt
41datastructure-1.5.dist-info/RECORD
