Metadata-Version: 2.1
Name: 41datastructure
Version: 1.5
Summary: A library for data structures
